lgtm_ai/__init__.py
lgtm_ai/__main__.py
lgtm_ai/ai/__init__.py
lgtm_ai/ai/agent.py
lgtm_ai/ai/exceptions.py
lgtm_ai/ai/prompts.py
lgtm_ai/ai/schemas.py
lgtm_ai/ai/utils.py
lgtm_ai/base/__init__.py
lgtm_ai/base/constants.py
lgtm_ai/base/exceptions.py
lgtm_ai/base/schemas.py
lgtm_ai/base/utils.py
lgtm_ai/config/__init__.py
lgtm_ai/config/constants.py
lgtm_ai/config/exceptions.py
lgtm_ai/config/handler.py
lgtm_ai/config/utils.py
lgtm_ai/config/validators.py
lgtm_ai/formatters/__init__.py
lgtm_ai/formatters/base.py
lgtm_ai/formatters/constants.py
lgtm_ai/formatters/json.py
lgtm_ai/formatters/markdown.py
lgtm_ai/formatters/pretty.py
lgtm_ai/formatters/templates/metadata.md.j2
lgtm_ai/formatters/templates/review_comment.md.j2
lgtm_ai/formatters/templates/review_comments_section.md.j2
lgtm_ai/formatters/templates/review_guide.md.j2
lgtm_ai/formatters/templates/review_summary.md.j2
lgtm_ai/formatters/templates/snippet.md.j2
lgtm_ai/git/__init__.py
lgtm_ai/git/exceptions.py
lgtm_ai/git/parser.py
lgtm_ai/git/repository.py
lgtm_ai/git_client/__init__.py
lgtm_ai/git_client/base.py
lgtm_ai/git_client/exceptions.py
lgtm_ai/git_client/github.py
lgtm_ai/git_client/gitlab.py
lgtm_ai/git_client/schemas.py
lgtm_ai/git_client/utils.py
lgtm_ai/jira/__init__.py
lgtm_ai/jira/jira.py
lgtm_ai/mcp/__init__.py
lgtm_ai/mcp/__main__.py
lgtm_ai/py.typed
lgtm_ai/review/__init__.py
lgtm_ai/review/context.py
lgtm_ai/review/exceptions.py
lgtm_ai/review/guide.py
lgtm_ai/review/prompt_generators.py
lgtm_ai/review/reviewer.py
lgtm_ai/review/schemas.py
lgtm_ai/review/templates/review_prompt.txt.j2
lgtm_ai/review/templates/summarizing_prompt.txt.j2
lgtm_ai/validators.py
lgtm_ai-1.4.3.dist-info/METADATA
lgtm_ai-1.4.3.dist-info/WHEEL
lgtm_ai-1.4.3.dist-info/entry_points.txt
lgtm_ai-1.4.3.dist-info/licenses/LICENSE
lgtm_ai-1.4.3.dist-info/RECORD
