Metadata-Version: 2.4
Name: lgtm-ai
Version: 1.4.3
Summary: Your AI-powered code review companion
License-File: LICENSE
Keywords: AI,code-review,linting,static-analysis,machine-learning,developer-tools,automation
Author: Sergio Castillo Lara
Author-email: s.cast.lara@gmail.com
Requires-Python: >=3.12,<4
Classifier: Development Status :: 5 - Production/Stable
Classifier: Intended Audience :: Developers
Classifier: Topic :: Software Development :: Quality Assurance
Classifier: Topic :: Software Development :: Code Generators
Classifier: Topic :: Utilities
Classifier: Topic :: Scientific/Engineering :: Artificial Intelligence
Classifier: License :: OSI Approved :: MIT License
Classifier: Programming Language :: Python :: 3
Classifier: Programming Language :: Python :: 3.12
Classifier: Programming Language :: Python :: 3.13
Classifier: Programming Language :: Python :: 3.14
Classifier: Operating System :: OS Independent
Provides-Extra: mcp
Requires-Dist: click (>=8.1.7,<9.0.0)
Requires-Dist: fastmcp (>=2.12.4,<3.0.0) ; extra == "mcp"
Requires-Dist: gitpython (>=3.1.45,<4.0.0)
Requires-Dist: httpx (>=0.28.1,<0.29.0)
Requires-Dist: jinja2 (>=3.1.6,<4.0.0)
Requires-Dist: nest-asyncio (>=1.6.0,<2.0.0) ; extra == "mcp"
Requires-Dist: pydantic (>=2.10.3,<3.0.0)
Requires-Dist: pydantic-ai-slim[anthropic,google,mistral,openai] (>=1.0.0,<2.0.0)
Requires-Dist: pydantic-settings (>=2.10.1,<3.0.0)
Requires-Dist: pygithub (>=2.6.1,<3.0.0)
Requires-Dist: python-gitlab (>=5.1.0,<6.0.0)
Requires-Dist: rich (>=13.9.4,<14.0.0)
Project-URL: Changelog, https://github.com/elementsinteractive/lgtm-ai/releases
Project-URL: Documentation, https://github.com/elementsinteractive/lgtm-ai?tab=readme-ov-file#lgtm-ai
Project-URL: Homepage, https://github.com/elementsinteractive/lgtm-ai
Project-URL: Source, https://github.com/elementsinteractive/lgtm-ai
Project-URL: Tracker, https://github.com/elementsinteractive/lgtm-ai/issues
